whoisit/__init__.py
whoisit/bootstrap.py
whoisit/errors.py
whoisit/logger.py
whoisit/overrides.py
whoisit/parser.py
whoisit/query.py
whoisit/utils.py
whoisit/version.py
whoisit-4.0.0.dist-info/licenses/LICENSE
whoisit-4.0.0.dist-info/METADATA
whoisit-4.0.0.dist-info/WHEEL
whoisit-4.0.0.dist-info/top_level.txt
whoisit-4.0.0.dist-info/RECORD
