Metadata-Version: 2.4
Name: whoisit
Version: 4.0.0
Summary: A Python client to RDAP WHOIS-like services for internet resources.
Home-page: https://github.com/meeb/whoisit
Author: https://github.com/meeb
Author-email: meeb@meeb.org
Requires-Python: >=3.13
License-File: LICENSE
Requires-Dist: httpx>=0.28.1
Requires-Dist: python-dateutil>=2.9.0.post0
Requires-Dist: requests>=2.32.5
Requires-Dist: typing-extensions>=4.15.0
Dynamic: author
Dynamic: author-email
Dynamic: home-page
Dynamic: license-file
